logger/__init__.py
logger/adapters/__init__.py
logger/adapters/cli_logger.py
logger/adapters/dummy_logger.py
logger/adapters/struct_logger.py
logger/ports.py
python_hex_logger-0.0.1.dist-info/METADATA
python_hex_logger-0.0.1.dist-info/WHEEL
python_hex_logger-0.0.1.dist-info/RECORD
